python_driver/__init__.py
python_driver/drive_switch.py
python_driver/parker_ipa_driver.py
python_driver-0.0.2.dist-info/LICENSE
python_driver-0.0.2.dist-info/METADATA
python_driver-0.0.2.dist-info/WHEEL
python_driver-0.0.2.dist-info/top_level.txt
python_driver-0.0.2.dist-info/RECORD
