Metadata-Version: 2.1
Name: python-driver
Version: 0.0.2
Summary: parker motion ipa python driver
Home-page: https://gitlab.baneng.com/tools/parker-motion-ipa-python-driver.git@packaging
Author: Amelia Meng
Author-email: ymeng@bannerengineering.com
License: UNKNOWN
Project-URL: Bug Tracker, https://gitlab.baneng.com/tools/parker-motion-ipa-python-driver.git@packaging
Platform: UNKNOWN
Classifier: Programming Language :: Python :: 3
Classifier: License :: OSI Approved :: MIT License
Classifier: Operating System :: OS Independent
Requires-Python: >=3.6
License-File: LICENSE
